query_patterns/__init__.py
query_patterns/decorator.py
query_patterns/pattern.py
query_patterns/types.py
query_patterns/utils.py
query_patterns/cli/__init__.py
query_patterns/cli/main.py
query_patterns/cli/command/__init__.py
query_patterns/cli/command/django.py
query_patterns/cli/command/sqlalchemy.py
query_patterns/cli/command/sqlmodel.py
query_patterns/cli/runner/__init__.py
query_patterns/cli/runner/base.py
query_patterns/cli/runner/django.py
query_patterns/cli/runner/sqlalchemy.py
query_patterns/cli/runner/sqlmodel.py
query_patterns/cli/runner/types.py
query_patterns-0.1.12.dist-info/METADATA
query_patterns-0.1.12.dist-info/WHEEL
query_patterns-0.1.12.dist-info/entry_points.txt
query_patterns-0.1.12.dist-info/top_level.txt
query_patterns-0.1.12.dist-info/RECORD
