Metadata-Version: 2.4
Name: query-patterns
Version: 0.1.12
Summary: Lightweight query access-pattern declaration for ORMs
Project-URL: GitHub, https://github.com/qu3vipon/query-patterns
Requires-Python: >=3.10
Requires-Dist: click>=8.1
Provides-Extra: sqlalchemy
Requires-Dist: sqlalchemy>=2.0; extra == "sqlalchemy"
Provides-Extra: django
Requires-Dist: django>=4.2; extra == "django"
Provides-Extra: sqlmodel
Requires-Dist: sqlmodel>=0.0.27; extra == "sqlmodel"
Provides-Extra: dev
Requires-Dist: pytest; extra == "dev"
Requires-Dist: tox; extra == "dev"
Requires-Dist: ruff; extra == "dev"
Requires-Dist: pre-commit; extra == "dev"
